quantum_image_classifier
