Metadata-Version: 2.1
Name: quantum-image-classifier
Version: 1.0.0
Summary: Quatum image classifier: A library of different quantum algorithms used to classify images
Home-page: https://github.com/jorgevazquezperez/Quantum-image-classifier
Author: Jorge Vázquez Pérez
Author-email: jorge.vazper@gmail.com
License: UNKNOWN
Keywords: qiskit quantum machine learning ml centroids
Platform: UNKNOWN
Classifier: Environment :: Console
Classifier: License :: OSI Approved :: Apache Software License
Classifier: Intended Audience :: Developers
Classifier: Intended Audience :: Science/Research
Classifier: Operating System :: Microsoft :: Windows
Classifier: Operating System :: POSIX :: Linux
Classifier: Programming Language :: Python :: 3.10
Classifier: Topic :: Scientific/Engineering
Requires-Python: <3.10
License-File: LICENSE
